> å…¬ä¼—å·ï¼š[å­—èŠ‚æ•°ç»„](https://p3-juejin.byteimg.com/tos-cn-i-k3u1fbpfcp/adbc507fc3704fd8955aae739a433db2~tplv-k3u1fbpfcp-zoom-1.image)
>
> å¸Œæœ›å¯¹ä½ æœ‰æ‰€å¸®åŠ© ğŸ¤£ğŸ¤£

Java å’Œ Kotlin çš„æ³›å‹ç®—ä½œæ˜¯ä¸€å—æŒºå¤§çš„çŸ¥è¯†éš¾ç‚¹äº†ï¼Œæ¶‰åŠåˆ°å¾ˆå¤šå¾ˆéš¾ç†è§£çš„æ¦‚å¿µï¼š**æ³›å‹å‹å‚ã€æ³›å‹å®å‚ã€ç±»å‹å‚æ•°ã€ä¸å˜ã€å‹å˜ã€åå˜ã€é€†å˜ã€å†…è”**ç­‰ç­‰ã€‚æœ¬ç¯‡æ–‡ç« å°±å°† Java å’Œ Kotlin ç»“åˆç€ä¸€èµ·è®²ï¼ŒæŒ‰ç…§æˆ‘çš„ä¸ªäººç†è§£æ¥é˜è¿°æ³›å‹çš„å„ä¸ªçŸ¥è¯†éš¾ç‚¹ï¼Œå¸Œæœ›å¯¹ä½ æœ‰æ‰€å¸®åŠ© ğŸ¤£ğŸ¤£

# ä¸€ã€æ³›å‹ç±»å‹

æ³›å‹å…è®¸ä½ å®šä¹‰å¸¦**ç±»å‹å½¢å‚**çš„æ•°æ®ç±»å‹ï¼Œå½“è¿™ç§ç±»å‹çš„å®ä¾‹è¢«åˆ›å»ºå‡ºæ¥åï¼Œ**ç±»å‹å½¢å‚**ä¾¿è¢«æ›¿æ¢ä¸ºç§°ä¸º**ç±»å‹å®å‚**çš„å…·ä½“ç±»å‹ã€‚ä¾‹å¦‚ï¼Œå¯¹äº `List<T>`ï¼ŒList ç§°ä¸º**åŸºç¡€ç±»å‹**ï¼ŒT ä¾¿æ˜¯**ç±»å‹å‹å‚**ï¼ŒT å¯ä»¥æ˜¯ä»»æ„ç±»å‹ï¼Œå½“æ²¡æœ‰æŒ‡å®š T çš„å…·ä½“ç±»å‹æ—¶ï¼Œæˆ‘ä»¬åªèƒ½çŸ¥é“`List<T>`æ˜¯ä¸€ä¸ªé›†åˆåˆ—è¡¨ï¼Œä½†ä¸çŸ¥é“æ‰¿è½½çš„å…·ä½“æ•°æ®ç±»å‹ã€‚è€Œå¯¹äº `List<String>`ï¼Œå½“ä¸­çš„ String ä¾¿æ˜¯**ç±»å‹å®å‚**ï¼Œæˆ‘ä»¬å¯ä»¥æ˜ç™½åœ°çŸ¥é“è¯¥åˆ—è¡¨æ‰¿è½½çš„éƒ½æ˜¯å­—ç¬¦ä¸²ï¼Œåœ¨è¿™é‡Œ String å°±ç›¸å½“äºä¸€ä¸ªå‚æ•°ä¼ é€’ç»™äº† Listï¼Œåœ¨è¿™è¯­ä¹‰ä¸‹ String ä¹Ÿç§°ä¸º**ç±»å‹å‚æ•°**

æ­¤å¤–ï¼Œåœ¨ Kotlin ä¸­æˆ‘ä»¬å¯ä»¥å®ç°**å®åŒ–ç±»å‹å‚æ•°**ï¼Œåœ¨è¿è¡Œæ—¶çš„**å†…è”å‡½æ•°**ä¸­æ‹¿åˆ°ä½œä¸º**ç±»å‹å®å‚**çš„å…·ä½“ç±»å‹ï¼Œå³å¯ä»¥å®ç° `T::class.java`ï¼Œä½†åœ¨ Java ä¸­å´æ— æ³•å®ç°ï¼Œå› ä¸º**å†…è”å‡½æ•°**æ˜¯ Kotlin ä¸­çš„æ¦‚å¿µï¼ŒJava ä¸­å¹¶ä¸å­˜åœ¨

# äºŒã€ä¸ºä»€ä¹ˆéœ€è¦æ³›å‹

æ³›å‹æ˜¯åœ¨ Java 5 ç‰ˆæœ¬å¼€å§‹å¼•å…¥çš„ï¼Œå…ˆé€šè¿‡å‡ ä¸ªå°ä¾‹å­æ¥æ˜ç™½æ³›å‹çš„é‡è¦æ€§

ä»¥ä¸‹ä»£ç å¯ä»¥æˆåŠŸç¼–è¯‘ï¼Œä½†æ˜¯åœ¨è¿è¡Œæ—¶å´æŠ›å‡ºäº† ClassCastExceptionã€‚äº†è§£ ArrayList æºç çš„åŒå­¦å°±çŸ¥é“å…¶å†…éƒ¨æ˜¯ç”¨ä¸€ä¸ª`Object[]`æ•°ç»„æ¥å­˜å‚¨æ•°æ®çš„ï¼Œè¿™ä½¿å¾— ArrayList èƒ½å¤Ÿå­˜å‚¨ä»»ä½•ç±»å‹çš„å¯¹è±¡ï¼Œæ‰€ä»¥åœ¨æ²¡æœ‰æ³›å‹çš„å¹´ä»£å¼€å‘è€…ä¸€ä¸å°å¿ƒå°±æœ‰å¯èƒ½å‘ ArrayList å­˜å…¥äº†éæœŸæœ›å€¼ï¼Œç¼–è¯‘æœŸå®Œå…¨æ­£å¸¸ï¼Œç­‰åˆ°åœ¨è¿è¡Œæ—¶å°±ä¼šæŠ›å‡ºç±»å‹è½¬æ¢å¼‚å¸¸äº†

```java
public class GenericTest {

    public static void main(String[] args) {
        List stringList = new ArrayList();
        addData(stringList);
        String str = (String) stringList.get(0);
    }

    public static void addData(List dataList) {
        dataList.add(1);
    }

}
```

```java
Exception in thread "main" java.lang.ClassCastException: 
java.lang.Integer cannot be cast to java.lang.String
```

è€Œæœ‰äº†æ³›å‹åï¼Œæˆ‘ä»¬å°±å¯ä»¥å†™å‡ºæ›´åŠ å¥å£®å®‰å…¨çš„ä»£ç ï¼Œä»¥ä¸‹é”™è¯¯å°±å®Œå…¨å¯ä»¥åœ¨ç¼–è¯‘é˜¶æ®µè¢«å‘ç°ï¼Œä¸”å–å€¼çš„æ—¶å€™ä¹Ÿä¸éœ€è¦è¿›è¡Œç±»å‹å¼ºè½¬

```java
public static void main(String[] args) {
    List<String> stringList = new ArrayList();
    addData(stringList); //æŠ¥é”™
    String str = stringList.get(0);
}

public static void addData(List<Integer> dataList) {
    dataList.add(1);
}
```

æ­¤å¤–ï¼Œåˆ©ç”¨æ³›å‹æˆ‘ä»¬å¯ä»¥å†™å‡ºæ›´åŠ å…·å¤‡é€šç”¨æ€§çš„ä»£ç ã€‚ä¾‹å¦‚ï¼Œå‡è®¾æˆ‘ä»¬éœ€è¦ä»ä¸€ä¸ª List ä¸­ç­›é€‰å‡ºå¤§äº 0 çš„å…¨éƒ¨æ•°å­—ï¼Œé‚£æˆ‘ä»¬è‡ªç„¶ä¸æƒ³ä¸º Integerã€Floatã€Double ç­‰å¤šç§ç±»å‹å„å†™ä¸€ä¸ªç­›é€‰æ–¹æ³•ï¼Œæ­¤æ—¶å°±å¯ä»¥åˆ©ç”¨æ³›å‹æ¥æŠ½è±¡ç­›é€‰é€»è¾‘

```java
public static void main(String[] args) {
    List<Integer> integerList = new ArrayList<>();
    integerList.add(-1);
    integerList.add(1);
    integerList.add(2);
    List<Integer> result1 = filter(integerList);

    List<Float> floatList = new ArrayList<>();
    floatList.add(-1f);
    floatList.add(1f);
    floatList.add(2f);
    List<Float> result2 = filter(floatList);
}

public static <T extends Number> List<T> filter(List<T> data) {
    List<T> filterList = new ArrayList<>();
    for (T datum : data) {
        if (datum.doubleValue() > 0) {
            filterList.add(datum);
        }
    }
    return filterList;
}
```

æ€»çš„æ¥è¯´ï¼Œæ³›å‹æœ‰ä»¥ä¸‹å‡ ç‚¹ä¼˜åŠ¿ï¼š

- ç±»å‹æ£€æŸ¥ï¼Œåœ¨ç¼–è¯‘é˜¶æ®µå°±èƒ½å‘ç°é”™è¯¯
- æ›´åŠ è¯­ä¹‰åŒ–ï¼Œçœ‹åˆ° `List<String>`æˆ‘ä»¬å°±çŸ¥é“å­˜å‚¨çš„æ•°æ®ç±»å‹æ˜¯ String
- è‡ªåŠ¨ç±»å‹è½¬æ¢ï¼Œåœ¨å–å€¼æ—¶æ— éœ€è¿›è¡Œæ‰‹åŠ¨ç±»å‹è½¬æ¢
- èƒ½å¤Ÿå°†é€»è¾‘æŠ½è±¡å‡ºæ¥ï¼Œä½¿å¾—ä»£ç æ›´åŠ å…·æœ‰é€šç”¨æ€§

# ä¸‰ã€ç±»å‹æ“¦é™¤

æ³›å‹æ˜¯åœ¨ Java 5 ç‰ˆæœ¬å¼€å§‹å¼•å…¥çš„ï¼Œæ‰€ä»¥åœ¨ Java 4 ä¸­ ArrayList è¿˜ä¸å±äºæ³›å‹ç±»ï¼Œå…¶å†…éƒ¨é€šè¿‡ **Object å‘ä¸Šè½¬å‹**å’Œ**å¤–éƒ¨å¼ºåˆ¶ç±»å‹è½¬æ¢**æ¥å®ç°æ•°æ®å­˜å‚¨å’Œé€»è¾‘å¤ç”¨ï¼Œæ­¤æ—¶å¼€å‘è€…çš„é¡¹ç›®ä¸­å·²ç»å……æ–¥äº†å¤§é‡ä»¥ä¸‹ç±»å‹çš„ä»£ç ï¼š

```java
List stringList = new ArrayList();
stringList.add("ä¸šå¿—é™ˆ");
stringList.add("https://juejin.cn/user/923245496518439");
String str = (String) stringList.get(0);
```

è€Œåœ¨æ¨å‡ºæ³›å‹çš„åŒæ—¶ï¼ŒJava å®˜æ–¹ä¹Ÿå¿…é¡»ä¿è¯äºŒè¿›åˆ¶çš„å‘åå…¼å®¹æ€§ï¼Œç”¨ Java 4 ç¼–è¯‘å‡ºçš„ Class æ–‡ä»¶ä¹Ÿå¿…é¡»èƒ½å¤Ÿåœ¨ Java 5 ä¸Šæ­£å¸¸è¿è¡Œï¼Œå³ Java 5 å¿…é¡»ä¿è¯ä»¥ä¸‹ä¸¤ç§ç±»å‹çš„ä»£ç èƒ½å¤Ÿåœ¨ Java 5 ä¸Šå…±å­˜ä¸”æ­£å¸¸è¿è¡Œ

```java
List stringList = new ArrayList();
List<String> stringList = new ArrayList();
```

ä¸ºäº†å®ç°è¿™ä¸€ç›®çš„ï¼ŒJava å°±é€šè¿‡**ç±»å‹æ“¦é™¤**è¿™ç§æ¯”è¾ƒåˆ«æ‰­çš„æ–¹å¼æ¥å®ç°æ³›å‹ã€‚ç¼–è¯‘å™¨åœ¨ç¼–è¯‘æ—¶ä¼šæ“¦é™¤ç±»å‹å®å‚ï¼Œåœ¨è¿è¡Œæ—¶ä¸å­˜åœ¨ä»»ä½•ç±»å‹ç›¸å…³çš„ä¿¡æ¯ï¼Œæ³›å‹å¯¹äº JVM æ¥è¯´æ˜¯é€æ˜çš„ï¼Œæœ‰æ³›å‹å’Œæ²¡æœ‰æ³›å‹çš„ä»£ç é€šè¿‡ç¼–è¯‘å™¨ç¼–è¯‘åæ‰€ç”Ÿæˆçš„äºŒè¿›åˆ¶ä»£ç æ˜¯å®Œå…¨ç›¸åŒçš„

ä¾‹å¦‚ï¼Œåˆ†åˆ«å£°æ˜ä¸¤ä¸ªæ³›å‹ç±»å’Œéæ³›å‹ç±»ï¼Œæ‹¿åˆ°å…¶ class æ–‡ä»¶

```java
public class GenericTest {

    public static class NodeA {

        private Object obj;

        public NodeA(Object obj) {
            this.obj = obj;
        }

    }

    public static class NodeB<T> {

        private T obj;

        public NodeB(T obj) {
            this.obj = obj;
        }

    }

    public static void main(String[] args) {
        NodeA nodeA = new NodeA("ä¸šå¿—é™ˆ");
        NodeB<String> nodeB = new NodeB<>("ä¸šå¿—é™ˆ");
        System.out.println(nodeB.obj);
    }

}
```

å¯ä»¥çœ‹åˆ° NodeA å’Œ NodeB ä¸¤ä¸ªå¯¹è±¡å¯¹åº”çš„å­—èŠ‚ç å…¶å®æ˜¯å®Œå…¨ä¸€æ ·çš„ï¼Œæœ€ç»ˆéƒ½æ˜¯ä½¿ç”¨ Object æ¥æ‰¿è½½æ•°æ®ï¼Œå°±å¥½åƒä¼ é€’ç»™ NodeB çš„ç±»å‹å‚æ•° String ä¸è§äº†ä¸€æ ·ï¼Œè¿™ä¾¿æ˜¯ç±»å‹æ“¦é™¤

```java
public class generic.GenericTest {
  public generic.GenericTest();
    Code:
       0: aload_0
       1: invokespecial #1                  // Method java/lang/Object."<init>":()V
       4: return

  public static void main(java.lang.String[]);
    Code:
       0: new           #2                  // class generic/GenericTest$NodeA
       3: dup
       4: ldc           #3                  // String ä¸šå¿—é™ˆ
       6: invokespecial #4                  // Method generic/GenericTest$NodeA."<init>":(Ljava/lang/Object;)V
       9: astore_1
      10: new           #5                  // class generic/GenericTest$NodeB
      13: dup
      14: ldc           #3                  // String ä¸šå¿—é™ˆ
      16: invokespecial #6                  // Method generic/GenericTest$NodeB."<init>":(Ljava/lang/Object;)V
      19: astore_2
      20: getstatic     #7                  // Field java/lang/System.out:Ljava/io/PrintStream;
      23: aload_2
      24: invokestatic  #8                  // Method generic/GenericTest$NodeB.access$000:(Lgeneric/GenericTest$NodeB;)Ljava/lang/Object;
      27: checkcast     #9                  // class java/lang/String
      30: invokevirtual #10                 // Method java/io/PrintStream.println:(Ljava/lang/String;)V
      33: return
}
```

è€Œå¦‚æœè®© NodeA ç›´æ¥ä½¿ç”¨ String ç±»å‹ï¼Œå¹¶ä¸”ä¸ºæ³›å‹ç±» NodeB è®¾å®šä¸Šç•Œçº¦æŸ Stringï¼Œä¸¤è€…çš„å­—èŠ‚ç ä¹Ÿä¼šå®Œå…¨ä¸€æ ·

```java
public class GenericTest {

    public static class NodeA {

        private String obj;

        public NodeA(String obj) {
            this.obj = obj;
        }

    }

    public static class NodeB<T extends String> {

        private T obj;

        public NodeB(T obj) {
            this.obj = obj;
        }

    }

    public static void main(String[] args) {
        NodeA nodeA = new NodeA("ä¸šå¿—é™ˆ");
        NodeB<String> nodeB = new NodeB<>("ä¸šå¿—é™ˆ");
        System.out.println(nodeB.obj);
    }

}
```

å¯ä»¥çœ‹åˆ° NodeA å’Œ NodeB çš„å­—èŠ‚ç æ˜¯å®Œå…¨ç›¸åŒçš„

```java
public class generic.GenericTest {
  public generic.GenericTest();
    Code:
       0: aload_0
       1: invokespecial #1                  // Method java/lang/Object."<init>":()V
       4: return

  public static void main(java.lang.String[]);
    Code:
       0: new           #2                  // class generic/GenericTest$NodeA
       3: dup
       4: ldc           #3                  // String ä¸šå¿—é™ˆ
       6: invokespecial #4                  // Method generic/GenericTest$NodeA."<init>":(Ljava/lang/String;)V
       9: astore_1
      10: new           #5                  // class generic/GenericTest$NodeB
      13: dup
      14: ldc           #3                  // String ä¸šå¿—é™ˆ
      16: invokespecial #6                  // Method generic/GenericTest$NodeB."<init>":(Ljava/lang/String;)V
      19: astore_2
      20: getstatic     #7                  // Field java/lang/System.out:Ljava/io/PrintStream;
      23: aload_2
      24: invokestatic  #8                  // Method generic/GenericTest$NodeB.access$000:(Lgeneric/GenericTest$NodeB;)Ljava/lang/String;
      27: invokevirtual #9                  // Method java/io/PrintStream.println:(Ljava/lang/String;)V
      30: return
}
```

æ‰€ä»¥è¯´ï¼Œå½“æ³›å‹ç±»å‹è¢«æ“¦é™¤åæœ‰ä¸¤ç§è½¬æ¢æ–¹å¼

- å¦‚æœæ³›å‹æ²¡æœ‰è®¾ç½®ä¸Šç•Œçº¦æŸï¼Œé‚£ä¹ˆå°†æ³›å‹è½¬åŒ–æˆ Object ç±»å‹
- å¦‚æœæ³›å‹è®¾ç½®äº†ä¸Šç•Œçº¦æŸï¼Œé‚£ä¹ˆå°†æ³›å‹è½¬åŒ–æˆè¯¥ä¸Šç•Œçº¦æŸ

è¯¥ç»“è®ºä¹Ÿå¯ä»¥é€šè¿‡åå°„æ³›å‹ç±»çš„ Class å¯¹è±¡æ¥éªŒè¯

```java
public class GenericTest {

    public static class NodeA<T> {

        private T obj;

        public NodeA(T obj) {
            this.obj = obj;
        }

    }

    public static class NodeB<T extends String> {

        private T obj;

        public NodeB(T obj) {
            this.obj = obj;
        }

    }

    public static void main(String[] args) {
        NodeA<String> nodeA = new NodeA<>("ä¸šå¿—é™ˆ");
        getField(nodeA.getClass());
        NodeB<String> nodeB = new NodeB<>("https://juejin.cn/user/923245496518439");
        getField(nodeB.getClass());
    }

    private static void getField(Class clazz) {
        for (Field field : clazz.getDeclaredFields()) {
            System.out.println("fieldName: " + field.getName());
            System.out.println("fieldTypeName: " + field.getType().getName());
        }
    }

}
```

NodeA å¯¹åº”çš„æ˜¯ Objectï¼ŒNodeB å¯¹åº”çš„æ˜¯ String

```java
fieldName: obj
fieldTypeName: java.lang.Object
fieldName: obj
fieldTypeName: java.lang.String
```

é‚£æ—¢ç„¶åœ¨è¿è¡Œæ—¶ä¸å­˜åœ¨ä»»ä½•ç±»å‹ç›¸å…³çš„ä¿¡æ¯ï¼Œæ³›å‹åˆä¸ºä»€ä¹ˆèƒ½å¤Ÿå®ç°**ç±»å‹æ£€æŸ¥**å’Œ**ç±»å‹è‡ªåŠ¨è½¬æ¢**ç­‰åŠŸèƒ½å‘¢ï¼Ÿ

å…¶å®ï¼Œç±»å‹æ£€æŸ¥æ˜¯ç¼–è¯‘å™¨åœ¨**ç¼–è¯‘å‰**å¸®æˆ‘ä»¬å®Œæˆçš„ï¼Œç¼–è¯‘å™¨çŸ¥é“æˆ‘ä»¬å£°æ˜çš„å…·ä½“çš„ç±»å‹å®å‚ï¼Œæ‰€ä»¥ç±»å‹æ“¦é™¤å¹¶ä¸å½±å“ç±»å‹æ£€æŸ¥åŠŸèƒ½ã€‚è€Œç±»å‹è‡ªåŠ¨è½¬æ¢å…¶å®æ˜¯é€šè¿‡å†…éƒ¨å¼ºåˆ¶ç±»å‹è½¬æ¢æ¥å®ç°çš„ï¼Œä¸Šé¢ç»™å‡ºçš„å­—èŠ‚ç ä¸­ä¹Ÿå¯ä»¥çœ‹åˆ°æœ‰ä¸€æ¡ç±»å‹å¼ºè½¬ checkcast çš„è¯­å¥

```java
27: checkcast     #9                  // class java/lang/String
```

ä¾‹å¦‚ï¼ŒArrayList å†…éƒ¨è™½ç„¶ç”¨äºå­˜å‚¨æ•°æ®çš„æ˜¯ Object æ•°ç»„ï¼Œä½† get æ–¹æ³•å†…éƒ¨ä¼šè‡ªåŠ¨å®Œæˆç±»å‹å¼ºè½¬

```java
transient Object[] elementData;
    
public E get(int index) {
	rangeCheck(index);
	return elementData(index);
}
    
@SuppressWarnings("unchecked")
E elementData(int index) {
	//å¼ºåˆ¶ç±»å‹è½¬æ¢
	return (E) elementData[index];
}
```

æ‰€ä»¥ Java çš„æ³›å‹å¯ä»¥çœ‹åšæ˜¯ä¸€ç§ç‰¹æ®Šçš„è¯­æ³•ç³–ï¼Œå› æ­¤ä¹Ÿè¢«äººç§°ä¸º**ä¼ªæ³›å‹**

# å››ã€ç±»å‹æ“¦é™¤çš„åé—ç—‡

Java æ³›å‹å¯¹äºç±»å‹çš„çº¦æŸåªåœ¨ç¼–è¯‘æœŸå­˜åœ¨ï¼Œè¿è¡Œæ—¶ä»ç„¶ä¼šæŒ‰ç…§ Java 5 ä¹‹å‰çš„æœºåˆ¶æ¥è¿è¡Œï¼Œæ³›å‹çš„å…·ä½“ç±»å‹åœ¨è¿è¡Œæ—¶å·²ç»è¢«åˆ é™¤äº†ï¼Œæ‰€ä»¥ JVM æ˜¯è¯†åˆ«ä¸åˆ°æˆ‘ä»¬åœ¨ä»£ç ä¸­æŒ‡å®šçš„å…·ä½“çš„æ³›å‹ç±»å‹çš„

ä¾‹å¦‚ï¼Œè™½ç„¶`List<String>`åªèƒ½ç”¨äºæ·»åŠ å­—ç¬¦ä¸²ï¼Œä½†æˆ‘ä»¬åªèƒ½**æ³›åŒ–åœ°**è¯†åˆ«åˆ°å®ƒå±äº`List<?>`ç±»å‹ï¼Œè€Œæ— æ³•å…·ä½“åˆ¤æ–­å‡ºè¯¥ List å†…éƒ¨åŒ…å«çš„å…·ä½“ç±»å‹

```java
List<String> stringList = new ArrayList<>();
//æ­£å¸¸
if (stringList instanceof ArrayList<?>) {

}
//æŠ¥é”™
if (stringList instanceof ArrayList<String>) {

}
```

æˆ‘ä»¬åªèƒ½å¯¹å…·ä½“çš„å¯¹è±¡å®ä¾‹è¿›è¡Œç±»å‹æ ¡éªŒï¼Œä½†æ— æ³•åˆ¤æ–­å‡ºæ³›å‹å½¢å‚çš„å…·ä½“ç±»å‹

```java
public <T> void filter(T data) {
	//æ­£å¸¸
	if (data instanceof String) {

	}
	//æŠ¥é”™
	if (T instanceof String) {

	}
	//æŠ¥é”™
	Class<T> tClass = T::getClass;
}
```

æ­¤å¤–ï¼Œç±»å‹æ“¦é™¤ä¹Ÿä¼šå¯¼è‡´ Java ä¸­å‡ºç°å¤šæ€é—®é¢˜ã€‚ä¾‹å¦‚ï¼Œä»¥ä¸‹ä¸¤ä¸ªæ–¹æ³•çš„æ–¹æ³•ç­¾åå¹¶ä¸å®Œå…¨ç›¸åŒï¼Œä½†ç”±äºç±»å‹æ“¦é™¤çš„åŸå› ï¼Œå…¥å‚å‚æ•°çš„æ•°æ®ç±»å‹éƒ½ä¼šè¢«çœ‹æˆ `List<Object>`ï¼Œä»è€Œå¯¼è‡´ä¸¤è€…æ— æ³•å…±å­˜åœ¨åŒä¸€ä¸ªåŒºåŸŸå†…

```java
public void filter(List<String> stringList) {

}

public void filter(List<Integer> stringList) {

}
```

# äº”ã€Kotlin æ³›å‹

Kotlin æ³›å‹åœ¨å¤§ä½“ä¸Šå’Œ Java ä¸€è‡´ï¼Œæ¯•ç«Ÿä¸¤è€…éœ€è¦ä¿è¯å…¼å®¹æ€§

```kotlin
class Plate<T>(val t: T) {

    fun cut() {
        println(t.toString())
    }

}

class Apple

class Banana

fun main() {
    val plateApple = Plate<Apple>(Apple())
    //æ³›å‹ç±»å‹è‡ªåŠ¨æ¨å¯¼
    val plateBanana = Plate(Banana())
    plateApple.cut()
    plateBanana.cut()
}
```

Kotlin ä¹Ÿæ”¯æŒåœ¨æ‰©å±•å‡½æ•°ä¸­ä½¿ç”¨æ³›å‹

```kotlin
fun <T> List<T>.find(t: T): T? {
    val index = indexOf(t)
    return if (index > -1) get(index) else null
}
```

éœ€è¦æ³¨æ„çš„æ˜¯ï¼Œä¸ºäº†å®ç°å‘åå…¼å®¹ï¼Œç›®å‰é«˜ç‰ˆæœ¬ Java ä¾ç„¶å…è®¸å®ä¾‹åŒ–æ²¡æœ‰å…·ä½“ç±»å‹å‚æ•°çš„æ³›å‹ç±»ï¼Œè¿™å¯ä»¥è¯´æ˜¯ä¸€ä¸ªå¯¹æ–°ç‰ˆæœ¬ JDK å±é™©ä½†å¯¹æ—§ç‰ˆæœ¬å‹å¥½çš„å…¼å®¹æªæ–½ã€‚ä½† Kotlin è¦æ±‚åœ¨ä½¿ç”¨æ³›å‹æ—¶éœ€è¦**æ˜¾å¼å£°æ˜æ³›å‹ç±»å‹**æˆ–è€…æ˜¯**ç¼–è¯‘å™¨èƒ½å¤Ÿç±»å‹æ¨å¯¼å‡ºå…·ä½“ç±»å‹**ï¼Œä»»ä½•ä¸å…·å¤‡å…·ä½“æ³›å‹ç±»å‹çš„æ³›å‹ç±»éƒ½æ— æ³•è¢«å®ä¾‹åŒ–ã€‚å› ä¸º Kotlin ä¸€å¼€å§‹å°±æ˜¯åŸºäº Java 6 ç‰ˆæœ¬çš„ï¼Œä¸€å¼€å§‹å°±å­˜åœ¨äº†æ³›å‹ï¼Œè‡ªç„¶å°±ä¸å­˜åœ¨éœ€è¦å…¼å®¹è€ä»£ç çš„é—®é¢˜ï¼Œå› æ­¤ä»¥ä¸‹ä¾‹å­å’Œ Java ä¼šæœ‰ä¸åŒçš„è¡¨ç°

```kotlin
val arrayList1 = ArrayList() //é”™è¯¯ï¼Œç¼–è¯‘å™¨æŠ¥é”™

val arrayList2 = arrayListOf<Int>() //æ­£å¸¸

val arrayList3 = arrayListOf(1, 2, 3) //æ­£å¸¸
```

è¿˜æœ‰ä¸€ä¸ªæ¯”è¾ƒå®¹æ˜“è®©äººè¯¯è§£çš„ç‚¹ã€‚æˆ‘ä»¬ç»å¸¸ä¼šä½¿ç”¨ `as` å’Œ `as?` æ¥è¿›è¡Œç±»å‹è½¬æ¢ï¼Œä½†å¦‚æœè½¬æ¢å¯¹è±¡æ˜¯æ³›å‹ç±»å‹çš„è¯ï¼Œé‚£å°±ä¼šç”±äºç±»å‹æ“¦é™¤è€Œå‡ºç°è¯¯åˆ¤ã€‚å¦‚æœè½¬æ¢å¯¹è±¡æœ‰æ­£ç¡®çš„**åŸºç¡€ç±»å‹**ï¼Œé‚£ä¹ˆè½¬æ¢å°±ä¼šæˆåŠŸï¼Œè€Œä¸ç®¡ç±»å‹å®å‚æ˜¯å¦ç›¸ç¬¦ã€‚å› ä¸ºåœ¨è¿è¡Œæ—¶è½¬æ¢å‘ç”Ÿçš„æ—¶å€™ç±»å‹å®å‚æ˜¯æœªçŸ¥çš„ï¼Œæ­¤æ—¶ç¼–è¯‘å™¨åªä¼šå‘å‡º â€œunchecked castâ€ è­¦å‘Šï¼Œä»£ç è¿˜æ˜¯å¯ä»¥æ­£å¸¸ç¼–è¯‘çš„

ä¾‹å¦‚ï¼Œåœ¨ä»¥ä¸‹ä¾‹å­ä¸­ä»£ç çš„è¿è¡Œç»“æœè¿˜ç¬¦åˆæˆ‘ä»¬çš„é¢„çŸ¥ã€‚ç¬¬ä¸€ä¸ªè½¬æ¢æ“ä½œç”±äºç±»å‹ç›¸ç¬¦ï¼Œæ‰€ä»¥æ‰“å°å‡ºäº†ç›¸åŠ å€¼ã€‚ç¬¬äºŒä¸ªè½¬æ¢æ“ä½œç”±äºåŸºç¡€ç±»å‹æ˜¯ Set è€Œé Listï¼Œæ‰€ä»¥æŠ›å‡ºäº† IllegalAccessException

```kotlin
fun main() {
    printSum(listOf(1, 2, 3)) //6
    printSum(setOf(1, 2, 3)) //IllegalAccessException
}

fun printSum(c: Collection<*>) {
    val intList = c as? List<Int> ?: throw IllegalAccessException("List is expected")
    println(intList.sum())
}
```

è€Œåœ¨ä»¥ä¸‹ä¾‹å­ä¸­æŠ›å‡ºçš„å´æ˜¯ ClassCastExceptionï¼Œè¿™æ˜¯å› ä¸ºåœ¨è¿è¡Œæ—¶ä¸ä¼šåˆ¤æ–­ä¸”æ— æ³•åˆ¤æ–­å‡ºç±»å‹å®å‚åˆ°åº•æ˜¯å¦æ˜¯ Intï¼Œè€Œåªä¼šåˆ¤æ–­åŸºç¡€ç±»å‹ List æ˜¯å¦ç›¸ç¬¦ï¼Œæ‰€ä»¥ `as?` æ“ä½œä¼šæˆåŠŸï¼Œç­‰åˆ°è¦æ‰§è¡Œç›¸åŠ æ“ä½œæ—¶æ‰ä¼šå‘ç°æ‹¿åˆ°çš„æ˜¯ String è€Œé Number

```kotlin
printSum(listOf("1", "2", "3"))

Exception in thread "main" java.lang.ClassCastException: 
java.lang.String cannot be cast to java.lang.Number
```

# å…­ã€ä¸Šç•Œçº¦æŸ

æ³›å‹æœ¬èº«å·²ç»å¸¦æœ‰ç±»å‹çº¦æŸçš„ä½œç”¨ï¼Œæˆ‘ä»¬ä¹Ÿå¯ä»¥è¿›ä¸€æ­¥ç»†åŒ–å…¶æ”¯æŒçš„å…·ä½“ç±»å‹

ä¾‹å¦‚ï¼Œå‡è®¾å­˜åœ¨ä¸€ä¸ªç›˜å­ Plateï¼Œæˆ‘ä»¬è¦æ±‚è¯¥ Plate åªèƒ½ç”¨äºè£…æ°´æœ Fruitï¼Œé‚£ä¹ˆå°±å¯ä»¥å¯¹å…¶æ³›å‹å£°æ˜åšè¿›ä¸€æ­¥çº¦æŸï¼ŒJava ä¸­ä½¿ç”¨ extend å…³é”®å­—æ¥å£°æ˜çº¦æŸè§„åˆ™ï¼Œè€Œ Kotlin ä½¿ç”¨çš„æ˜¯ **:**  ã€‚è¿™æ · Plate å°±åªèƒ½ç”¨äº Fruit å’Œå…¶å­ç±»ï¼Œè€Œæ— æ³•ç”¨äº Noodles ç­‰ä¸ç›¸å…³çš„ç±»å‹ï¼Œè¿™ç§ç±»å‹çº¦æŸå°±è¢«ç§°ä¸º**ä¸Šç•Œçº¦æŸ**

```kotlin
open class Fruit

class Apple : Fruit()

class Noodles

class Plate<T : Fruit>(val t: T)

fun main() {
    val applePlate = Plate(Apple()) //æ­£å¸¸
    val noodlesPlate = Plate(Noodles()) //æŠ¥é”™
}
```

å¦‚æœä¸Šç•Œçº¦æŸæ‹¥æœ‰å¤šå±‚ç±»å‹å…ƒç´ ï¼ŒJava æ˜¯ä½¿ç”¨ & ç¬¦å·è¿›è¡Œé“¾å¼å£°æ˜ï¼ŒKotlin åˆ™æ˜¯ç”¨ where å…³é”®å­—æ¥ä¾æ¬¡è¿›è¡Œå£°æ˜

```kotlin
interface Soft

class Plate<T>(val t: T) where T : Fruit, T : Soft

open class Fruit

class Apple : Fruit()

class Banana : Fruit(), Soft

fun main() {
    val applePlate = Plate(Apple()) //æŠ¥é”™
    val bananaPlate = Plate(Banana()) //æ­£å¸¸
}
```

æ­¤å¤–ï¼Œæ²¡æœ‰æŒ‡å®šä¸Šç•Œçº¦æŸçš„ç±»å‹å½¢å‚ä¼šé»˜è®¤ä½¿ç”¨ Any? ä½œä¸ºä¸Šç•Œï¼Œå³æˆ‘ä»¬å¯ä»¥ä½¿ç”¨ String æˆ– String? ä½œä¸ºå…·ä½“çš„ç±»å‹å®å‚ã€‚å¦‚æœæƒ³ç¡®ä¿æœ€ç»ˆçš„ç±»å‹å®å‚ä¸€å®šæ˜¯éç©ºç±»å‹ï¼Œé‚£ä¹ˆå°±éœ€è¦ä¸»åŠ¨å£°æ˜ä¸Šç•Œçº¦æŸä¸º Any

# ä¸ƒã€ç±»å‹é€šé…ç¬¦ & æ˜Ÿå·æŠ•å½±

å‡è®¾ç°åœ¨æœ‰ä¸ªéœ€æ±‚ï¼Œéœ€è¦æˆ‘ä»¬æä¾›ä¸€ä¸ªæ–¹æ³•ç”¨äºéå†æ‰€æœ‰ç±»å‹çš„ List é›†åˆå¹¶æ‰“å°å…ƒç´ 

ç¬¬ä¸€ç§åšæ³•å°±æ˜¯ç›´æ¥å°†æ–¹æ³•å‚æ•°ç±»å‹å£°æ˜ä¸º Listï¼Œä¸åŒ…å«ä»»ä½•æ³›å‹ç±»å‹å£°æ˜ã€‚è¿™ç§åšæ³•å¯è¡Œï¼Œä½†ç¼–è¯‘å™¨ä¼šè­¦å‘Šæ— æ³•ç¡®å®š `list`å…ƒç´ çš„å…·ä½“ç±»å‹ï¼Œæ‰€ä»¥è¿™ä¸æ˜¯æœ€ä¼˜è§£æ³•

```java
public static void printList1(List list) {
    for (Object o : list) {
        System.out.println(o);
    }
}
```

å¯èƒ½ä¼šæƒ³åˆ°çš„ç¬¬äºŒç§åšæ³•æ˜¯ï¼šå°†æ³›å‹ç±»å‹ç›´æ¥å£°æ˜ä¸º Objectï¼Œå¸Œæœ›è®©å…¶é€‚ç”¨äºä»»ä½•ç±»å‹çš„ Listã€‚è¿™ç§åšæ³•å®Œå…¨ä¸å¯è¡Œï¼Œå› ä¸ºå³ä½¿ `String` æ˜¯ `Object` çš„å­ç±»ï¼Œä½† `List<String>` å’Œ `List<Object>`å¹¶ä¸å…·å¤‡ä»å±å…³ç³»ï¼Œè¿™å¯¼è‡´ `printList2` æ–¹æ³•å®é™…ä¸Šåªèƒ½ç”¨äº`List<Object>`è¿™ä¸€ç§å…·ä½“ç±»å‹

```java
public static void printList2(List<Object> list) {
    for (Object o : list) {
        System.out.println(o);
    }
}
```

æœ€ä¼˜è§£æ³•å°±æ˜¯è¦ç”¨åˆ° Java çš„ç±»å‹é€šé…ç¬¦ **?** äº†ï¼Œ`printList3`æ–¹æ³•å®Œå…¨å¯è¡Œä¸”ç¼–è¯‘å™¨ä¹Ÿä¸ä¼šè­¦å‘ŠæŠ¥é”™

```java
public static void printList3(List<?> list) {
    for (Object o : list) {
        System.out.println(o);
    }
}
```

ï¼Ÿ è¡¨ç¤ºæˆ‘ä»¬å¹¶ä¸å…³å¿ƒå…·ä½“çš„æ³›å‹ç±»å‹ï¼Œè€Œåªæ˜¯æƒ³é…åˆå…¶å®ƒç±»å‹è¿›è¡Œä¸€äº›æ¡ä»¶é™åˆ¶ã€‚ä¾‹å¦‚ï¼Œ`printList3`æ–¹æ³•å¸Œæœ›ä¼ å…¥çš„æ˜¯ä¸€ä¸ª Listï¼Œä½†ä¸é™åˆ¶æ³›å‹çš„å…·ä½“ç±»å‹ï¼Œæ­¤æ—¶`List<?>`å°±è¾¾åˆ°äº†è¿™ä¸€å±‚é™åˆ¶æ¡ä»¶

ç±»å‹é€šé…ç¬¦ä¹Ÿå­˜åœ¨ç€ä¸€äº›é™åˆ¶ã€‚å› ä¸º `printList3` æ–¹æ³•å¹¶ä¸åŒ…å«å…·ä½“çš„æ³›å‹ç±»å‹ï¼Œæ‰€ä»¥æˆ‘ä»¬ä»ä¸­å–å‡ºçš„å€¼åªèƒ½æ˜¯ Object ç±»å‹ï¼Œä¸”æ— æ³•å‘å…¶æ’å…¥å€¼ï¼Œè¿™éƒ½æ˜¯ä¸ºäº†é¿å…å‘ç”Ÿ ClassCastException

Java çš„**ç±»å‹é€šé…ç¬¦**å¯¹åº” Kotlin ä¸­çš„æ¦‚å¿µå°±æ˜¯**æ˜Ÿå·æŠ•å½± * **ï¼ŒJava å­˜åœ¨çš„é™åˆ¶åœ¨ Kotlin ä¸­ä¸€æ ·æœ‰

```kotlin
fun printList(list: List<*>) {
    for (any in list) {
        println(any)
    }
}
```

æ­¤å¤–ï¼Œæ˜Ÿå·æŠ•å½±åªèƒ½å‡ºç°åœ¨**ç±»å‹å½¢å‚**çš„ä½ç½®ï¼Œä¸èƒ½ä½œä¸º**ç±»å‹å®å‚**

```kotlin
val list: MutableList<*> = ArrayList<Number>() //æ­£å¸¸

val list2: MutableList<*> = ArrayList<*>() //æŠ¥é”™
```

# å…«ã€åå˜ & ä¸å˜

çœ‹ä»¥ä¸‹ä¾‹å­ã€‚Apple å’Œ Banana éƒ½æ˜¯ Fruit çš„å­ç±»ï¼Œå¯ä»¥å‘ç° Apple[] ç±»å‹çš„å¯¹è±¡æ˜¯å¯ä»¥èµ‹å€¼ç»™ Fruit[] çš„ï¼Œä¸” Fruit[] å¯ä»¥å®¹çº³ Apple å¯¹è±¡å’Œ Banana å¯¹è±¡ï¼Œè¿™ç§è®¾è®¡å°±è¢«ç§°ä¸º**åå˜**ï¼Œå³å¦‚æœ A æ˜¯ B çš„å­ç±»ï¼Œé‚£ä¹ˆ A[] å°±æ˜¯ B[] çš„å­ç±»å‹ã€‚ç›¸å¯¹çš„ï¼ŒObject[] å°±æ˜¯æ‰€æœ‰æ•°ç»„å¯¹è±¡çš„çˆ¶ç±»å‹

```java
static class Fruit {

}

static class Apple extends Fruit {

}

static class Banana extends Fruit {

}

public static void main(String[] args) {
    Fruit[] fruitArray = new Apple[10];
    //æ­£å¸¸
    fruitArray[0] = new Apple();
    //ç¼–è¯‘æ—¶æ­£å¸¸ï¼Œè¿è¡Œæ—¶æŠ›å‡º ArrayStoreException
    fruitArray[1] = new Banana();
}
```

è€Œ Java ä¸­çš„æ³›å‹æ˜¯**ä¸å˜**çš„ï¼Œè¿™æ„å‘³ç€ String è™½ç„¶æ˜¯ Object çš„å­ç±»ï¼Œä½†`List<String>`å¹¶ä¸æ˜¯`List<Object>`çš„å­ç±»å‹ï¼Œä¸¤è€…å¹¶ä¸å…·å¤‡ç»§æ‰¿å…³ç³»

```java
List<String> stringList = new ArrayList<>();
List<Object> objectList = stringList; //æŠ¥é”™
```

é‚£ä¸ºä»€ä¹ˆ Java ä¸­çš„æ³›å‹æ˜¯**ä¸å˜**çš„å‘¢ï¼Ÿ

è¿™å¯ä»¥é€šè¿‡çœ‹ä¸€ä¸ªä¾‹å­æ¥è§£é‡Šã€‚å‡è®¾ Java ä¸­çš„æ³›å‹æ˜¯**åå˜**çš„ï¼Œé‚£ä¹ˆä»¥ä¸‹ä»£ç å°±å¯ä»¥æˆåŠŸé€šè¿‡ç¼–è¯‘é˜¶æ®µçš„æ£€æŸ¥ï¼Œåœ¨è¿è¡Œæ—¶å°±ä¸å¯é¿å…åœ°å°†æŠ›å‡º ClassCastExceptionï¼Œè€Œå¼•å…¥æ³›å‹çš„åˆè¡·å°±æ˜¯ä¸ºäº†å®ç°ç±»å‹å®‰å…¨ï¼Œæ”¯æŒåå˜çš„è¯é‚£æ³›å‹ä¹Ÿå°±æ²¡æœ‰æ¯”æ•°ç»„å®‰å…¨å¤šå°‘äº†ï¼Œå› æ­¤å°±å°†æ³›å‹è¢«è®¾è®¡ä¸º**ä¸å˜**çš„

```java
List<String> strList = new ArrayList<>();
List<Object> objs = strList; //å‡è®¾å¯ä»¥è¿è¡Œï¼Œå®é™…ä¸Šç¼–è¯‘å™¨ä¼šæŠ¥é”™
objs.add(1);
String str = strList.get(0); //å°†æŠ›å‡º ClassCastExceptionï¼Œæ— æ³•å°†æ•´æ•°è½¬æ¢ä¸ºå­—ç¬¦ä¸²
```

å†æ¥æƒ³ä¸ªé—®é¢˜ï¼Œæ—¢ç„¶**åå˜**æœ¬èº«å¹¶ä¸å®‰å…¨ï¼Œé‚£ä¹ˆæ•°ç»„ä¸ºä½•åˆè¦è¢«è®¾è®¡ä¸ºåå˜å‘¢ï¼Ÿ

Arrays ç±»åŒ…å«ä¸€ä¸ª `equals`æ–¹æ³•ç”¨äºæ¯”è¾ƒä¸¤ä¸ªæ•°ç»„å¯¹è±¡æ˜¯å¦ç›¸ç­‰ã€‚å¦‚æœæ•°ç»„æ˜¯åå˜çš„ï¼Œé‚£ä¹ˆå°±éœ€è¦ä¸ºæ¯ä¸€ç§æ•°ç»„å¯¹è±¡éƒ½å®šä¹‰ä¸€ä¸ª `equals`æ–¹æ³•ï¼ŒåŒ…æ‹¬å¼€å‘è€…è‡ªå®šä¹‰çš„æ•°æ®ç±»å‹ã€‚æƒ³è¦é¿å…è¿™ç§æƒ…å†µï¼Œå°±éœ€è¦è®© Object[] å¯ä»¥æ¥æ”¶ä»»æ„æ•°ç»„ç±»å‹ï¼Œå³**è®© Object[] æˆä¸ºæ‰€æœ‰æ•°ç»„å¯¹è±¡çš„çˆ¶ç±»å‹**ï¼Œè¿™å°±ä½¿å¾—æ•°ç»„å¿…é¡»æ”¯æŒåå˜ï¼Œè¿™æ ·å¤šæ€æ‰èƒ½ç”Ÿæ•ˆ

```java
public class Arrays {
    
     public static boolean equals(Object[] a, Object[] a2) {
        if (a==a2)
            return true;
        if (a==null || a2==null)
            return false;

        int length = a.length;
        if (a2.length != length)
            return false;

        for (int i=0; i<length; i++) {
            Object o1 = a[i];
            Object o2 = a2[i];
            if (!(o1==null ? o2==null : o1.equals(o2)))
                return false;
        }

        return true;
    }
    
}
```

éœ€è¦æ³¨æ„çš„æ˜¯ï¼ŒKotlin ä¸­çš„æ•°ç»„å’Œ Java ä¸­çš„æ•°ç»„å¹¶ä¸ä¸€æ ·ï¼ŒKotlin æ•°ç»„å¹¶ä¸æ”¯æŒåå˜ï¼ŒKotlin æ•°ç»„ç±»ä¼¼äºé›†åˆæ¡†æ¶ï¼Œå…·æœ‰å¯¹åº”çš„å®ç°ç±» Arrayï¼ŒArray å±äºæ³›å‹ç±»ï¼Œæ”¯æŒäº†æ³›å‹å› æ­¤ä¹Ÿä¸å†åå˜

```kotlin
val stringArray = arrayOfNulls<String>(3)
val anyArray: Array<Any?> = stringArray //æŠ¥é”™
```

> Java çš„æ³›å‹ä¹Ÿå¹¶éå®Œå…¨**ä¸å˜**çš„ï¼Œåªæ˜¯å®ç°**åå˜**éœ€è¦æ»¡è¶³ä¸€äº›æ¡ä»¶ï¼Œç”šè‡³ä¹Ÿå¯ä»¥å®ç°**é€†å˜**ï¼Œä¸‹é¢å°±æ¥ä»‹ç»ä¸‹æ³›å‹å¦‚ä½•å®ç°**åå˜**å’Œ**é€†å˜**

# ä¹ã€æ³›å‹åå˜

å‡è®¾æˆ‘ä»¬å®šä¹‰äº†ä¸€ä¸ª`copyAll`å¸Œæœ›ç”¨äº List æ•°æ®è¿ç§»ã€‚é‚£ä»¥ä¸‹æ“ä½œåœ¨æˆ‘ä»¬çœ‹æ¥å°±æ˜¯å®Œå…¨å®‰å…¨çš„ï¼Œå› ä¸º Integer æ˜¯ Number çš„å­ç±»ï¼ŒæŒ‰é“ç†æ¥è¯´æ˜¯èƒ½å¤Ÿå°† Integer ä¿å­˜ä¸º Number çš„ï¼Œä½†ç”±äºæ³›å‹ä¸å˜æ€§ï¼Œ`List<Integer>`å¹¶ä¸æ˜¯`List<Number>`çš„å­ç±»å‹ï¼Œæ‰€ä»¥å®é™…ä¸Šè¯¥æ“ä½œå°†æŠ¥é”™

```java
public static void main(String[] args) {
    List<Number> numberList = new ArrayList<>();

    List<Integer> integerList = new ArrayList<>();
    integerList.add(1);
    integerList.add(2);
    integerList.add(3);

    copyAll(numberList, integerList); //æŠ¥é”™
}

private static <T> void copyAll(List<T> to, List<T> from) {
    to.addAll(from);
}
```

æ€è€ƒä¸‹è¯¥æ“ä½œä¸ºä»€ä¹ˆä¼šæŠ¥é”™ï¼Ÿ

ç¼–è¯‘å™¨çš„ä½œç”¨ä¹‹ä¸€å°±æ˜¯**è¿›è¡Œå®‰å…¨æ£€æŸ¥å¹¶é˜»æ­¢å¯èƒ½å‘ç”Ÿä¸å®‰å…¨è¡Œä¸ºçš„æ“ä½œ**ï¼Œ`copyAll` æ–¹æ³•ä¼šæŠ¥é”™ï¼Œé‚£ä¹ˆè‚¯å®šå°±æ˜¯ç¼–è¯‘å™¨è§‰å¾—è¯¥æ–¹æ³•æœ‰å¯èƒ½ä¼šè§¦å‘ä¸å®‰å…¨çš„æ“ä½œã€‚å¼€å‘è€…çš„æœ¬æ„æ˜¯å¸Œæœ›å°† Integer ç±»å‹çš„æ•°æ®è½¬ç§»åˆ° NumberList ä¸­ï¼Œåªæœ‰è¿™ç§æ“ä½œä¸”è¿™ç§æ“ä½œåœ¨æˆ‘ä»¬çœ‹æ¥è‚¯å®šæ˜¯å®‰å…¨çš„ï¼Œä½†æ˜¯ç¼–è¯‘å™¨ä¸çŸ¥é“å¼€å‘è€…æœ€ç»ˆæ‰€è¦åšçš„å…·ä½“æ“ä½œå•Š

å‡è®¾ `copyAll`æ–¹æ³•å¯ä»¥æ­£å¸¸è°ƒç”¨ï¼Œé‚£ä¹ˆ`copyAll`æ–¹æ³•è‡ªç„¶åªä¼šæŠŠ `from` å½“åš `List<Number>`æ¥çœ‹å¾…ã€‚å› ä¸º Integer æ˜¯ Number çš„å­ç±»ï¼Œä» `integerList` è·å–åˆ°çš„æ•°æ®å¯¹äº `numberList` æ¥è¯´è‡ªç„¶æ˜¯å®‰å…¨çš„ã€‚è€Œå¦‚æœæˆ‘ä»¬åœ¨`copyAll`æ–¹æ³•ä¸­å·å·å‘ `integerList` ä¼ å…¥äº†ä¸€ä¸ª Number ç±»å‹çš„å€¼çš„è¯ï¼Œé‚£ä¹ˆè‡ªç„¶å°±å°†æŠ›å‡ºå¼‚å¸¸ï¼Œå› ä¸º from å®é™…ä¸Šæ˜¯ `List<Integer>`ç±»å‹

ä¸ºäº†é˜»æ­¢è¿™ç§ä¸å®‰å…¨çš„è¡Œä¸ºï¼Œç¼–è¯‘å™¨é€‰æ‹©é€šè¿‡ç›´æ¥æŠ¥é”™æ¥è¿›è¡Œæç¤ºã€‚ä¸ºäº†è§£å†³æŠ¥é”™ï¼Œæˆ‘ä»¬å°±éœ€è¦å‘ç¼–è¯‘å™¨åšå‡ºå®‰å…¨ä¿è¯ï¼š**ä» from å–å‡ºæ¥çš„å€¼åªä¼šå½“åš Number ç±»å‹ï¼Œä¸”ä¸ä¼šå‘ from ä¼ å…¥ä»»ä½•å€¼**

ä¸ºäº†è¾¾æˆä»¥ä¸Šä¿è¯ï¼Œéœ€è¦ä¿®æ”¹ä¸‹ `copyAll` æ–¹æ³•

```java
private static <T> void copyAll(List<T> to, List<? extends T> from) {
    to.addAll(from);
}
```

`? extends T` è¡¨ç¤º `from` æ¥å— T æˆ–è€… T çš„å­ç±»å‹ï¼Œè€Œä¸å•å•æ˜¯ T è‡ªèº«ï¼Œè¿™æ„å‘³ç€æˆ‘ä»¬å¯ä»¥å®‰å…¨åœ°ä» `from` ä¸­å–å€¼å¹¶å£°æ˜ä¸º T ç±»å‹ï¼Œä½†ç”±äºæˆ‘ä»¬å¹¶ä¸çŸ¥é“ T ä»£è¡¨çš„å…·ä½“ç±»å‹ï¼Œå†™å…¥æ“ä½œå¹¶ä¸å®‰å…¨ï¼Œå› æ­¤ç¼–è¯‘å™¨ä¼šé˜»æ­¢æˆ‘ä»¬å‘ `from` æ‰§è¡Œä¼ å€¼æ“ä½œã€‚æœ‰äº†è¯¥é™åˆ¶åï¼Œä»`integerList`ä¸­å–å‡ºæ¥çš„å€¼åªèƒ½æ˜¯å½“åš Number ç±»å‹ï¼Œä¸”é¿å…äº†å‘`integerList`æ’å…¥éæ³•å€¼çš„å¯èƒ½ï¼Œæ­¤æ—¶`List<Integer>`å°±ç›¸å½“äº`List<? extends Number>`çš„å­ç±»å‹äº†ï¼Œä»è€Œä½¿å¾— `copyAll` æ–¹æ³•å¯ä»¥æ­£å¸¸ä½¿ç”¨

ç®€è€Œè¨€ä¹‹ï¼Œå¸¦ **extends** é™å®šäº†ä¸Šç•Œçš„é€šé…ç¬¦ç±»å‹ä½¿å¾—**æ³›å‹å‚æ•°ç±»å‹æ˜¯åå˜çš„**ï¼Œå³å¦‚æœ A æ˜¯ B çš„å­ç±»ï¼Œé‚£ä¹ˆ `Generic<A>` å°±æ˜¯`Generic<? extends B>`çš„å­ç±»å‹

# åã€æ³›å‹é€†å˜

**åå˜**æ‰€èƒ½åšåˆ°çš„æ˜¯ï¼šå¦‚æœ A æ˜¯ B çš„å­ç±»ï¼Œé‚£ä¹ˆ `Generic<A>` å°±æ˜¯`Generic<? extends B>`çš„å­ç±»å‹ã€‚**é€†å˜**ç›¸åï¼Œå…¶ä»£è¡¨çš„æ˜¯ï¼šå¦‚æœ A æ˜¯ B çš„å­ç±»ï¼Œé‚£ä¹ˆ `Generic<B>` å°±æ˜¯ `Generic<? super A>` çš„å­ç±»å‹

åå˜è¿˜æ¯”è¾ƒå¥½ç†è§£ï¼Œæ¯•ç«Ÿå…¶ç»§æ‰¿å…³ç³»æ˜¯ç›¸åŒçš„ï¼Œä½†é€†å˜å°±æ¯”è¾ƒåç›´è§‰äº†ï¼Œæ•´ä¸ªç»§æ‰¿å…³ç³»éƒ½å€’è¿‡æ¥äº†

é€†å˜çš„ä½œç”¨å¯ä»¥é€šè¿‡ç›¸åŒçš„ä¾‹å­æ¥ç†è§£ï¼Œ`copyAll` æ–¹æ³•å¦‚ä¸‹ä¿®æ”¹ä¹Ÿå¯ä»¥æ­£å¸¸ä½¿ç”¨ï¼Œæ­¤æ—¶å°±æ˜¯å‘ç¼–è¯‘å™¨åšå‡ºäº†å¦ä¸€ç§å®‰å…¨ä¿è¯ï¼š**å‘ numberList ä¼ é€’çš„å€¼åªä¼šæ˜¯ Integer ç±»å‹ï¼Œä¸”ä» numberList å–å‡ºçš„å€¼ä¹Ÿåªä¼šå½“åš Object ç±»å‹**

```java
private static <T> void copyAll(List<? super T> to, List<T> from) {
    to.addAll(from);
}
```

`? super T`è¡¨ç¤º `to` æ¥æ”¶ T æˆ–è€… T çš„çˆ¶ç±»å‹ï¼Œè€Œä¸å•å•æ˜¯ T è‡ªèº«ï¼Œè¿™æ„å‘³ç€æˆ‘ä»¬å¯ä»¥å®‰å…¨åœ°å‘ `to` ä¼ ç±»å‹ä¸º T çš„å€¼ï¼Œä½†ç”±äºæˆ‘ä»¬å¹¶ä¸çŸ¥é“ T ä»£è¡¨çš„å…·ä½“ç±»å‹ï¼Œæ‰€ä»¥ä» `to` å–å‡ºæ¥çš„å€¼åªèƒ½æ˜¯ Object ç±»å‹ã€‚æœ‰äº†è¯¥é™åˆ¶åï¼Œ`integerList`åªèƒ½å‘ `numberList`ä¼ é€’ç±»å‹ä¸º Integer çš„å€¼ï¼Œä¸”é¿å…äº†ä» `numberList` ä¸­è·å–åˆ°éæ³•ç±»å‹å€¼çš„å¯èƒ½ï¼Œæ­¤æ—¶`List<Number>`å°±ç›¸å½“äº`List<? super Integer>`çš„å­ç±»å‹äº†ï¼Œä»è€Œä½¿å¾— `copyAll` æ–¹æ³•å¯ä»¥æ­£å¸¸ä½¿ç”¨

ç®€è€Œè¨€ä¹‹ï¼Œå¸¦ **super** é™å®šäº†ä¸‹ç•Œçš„é€šé…ç¬¦ç±»å‹ä½¿å¾—**æ³›å‹å‚æ•°ç±»å‹æ˜¯é€†å˜çš„**ï¼Œå³å¦‚æœ A æ˜¯ B çš„å­ç±»ï¼Œé‚£ä¹ˆ `Generic<B>` å°±æ˜¯ `Generic<? super A>` çš„å­ç±»å‹

# åä¸€ã€out  &  in

Java ä¸­å…³äºæ³›å‹çš„å›°å¢ƒåœ¨ Kotlin ä¸­ä¸€æ ·å­˜åœ¨ï¼Œout å’Œ in éƒ½æ˜¯ Kotlin çš„å…³é”®å­—ï¼Œå…¶ä½œç”¨éƒ½æ˜¯ä¸ºäº†æ¥åº”å¯¹æ³›å‹é—®é¢˜ã€‚`in` å’Œ `out` æ˜¯ä¸€ä¸ªå¯¹ç«‹é¢ï¼ŒåŒæ—¶å®ƒä»¬åˆä¸æ³›å‹**ä¸å˜**ç›¸å¯¹ç«‹ï¼Œç»Ÿç§°ä¸º**å‹å˜**

- out æœ¬èº«å¸¦æœ‰**å‡ºå»**çš„æ„æ€ï¼Œæœ¬èº«å¸¦æœ‰å€¾å‘äº**å–å€¼æ“ä½œ**çš„æ„æ€ï¼Œç”¨äº**æ³›å‹åå˜**
- in æœ¬èº«å¸¦æœ‰**è¿›æ¥**çš„æ„æ€ï¼Œæœ¬èº«å¸¦æœ‰å€¾å‘äº**ä¼ å€¼æ“ä½œ**çš„æ„æ€ï¼Œç”¨äº**æ³›å‹é€†å˜**

å†æ¥çœ‹ä¸‹ç›¸åŒä¾‹å­ï¼Œè¯¥ä¾‹å­åœ¨ Java ä¸­å­˜åœ¨çš„é—®é¢˜åœ¨ Kotlin ä¸­ä¸€æ ·æœ‰

```kotlin
fun main() {
    val numberList = mutableListOf<Number>()

    val intList = mutableListOf(1, 2, 3, 4)

    copyAll(numberList, intList) //æŠ¥é”™

    numberList.forEach {
        println(it)
    }
}

fun <T> copyAll(to: MutableList<T>, from: MutableList<T>) {
    to.addAll(from)
}
```

æŠ¥é”™åŸå› å’Œ Java å®Œå…¨ä¸€æ ·ï¼Œå› ä¸ºæ­¤æ—¶ç¼–è¯‘å™¨æ— æ³•åˆ¤æ–­å‡ºæˆ‘ä»¬åˆ°åº•æ˜¯å¦ä¼šåšå‡ºä¸å®‰å…¨çš„æ“ä½œï¼Œæ‰€ä»¥æˆ‘ä»¬ä¾ç„¶è¦æ¥å‘ç¼–è¯‘å™¨åšå‡ºå®‰å…¨ä¿è¯

æ­¤æ—¶å°±éœ€è¦åœ¨ Kotlin ä¸­æ¥å®ç°**æ³›å‹åå˜**å’Œ**æ³›å‹é€†å˜**äº†ï¼Œä»¥ä¸‹ä¸¤ç§æ–¹å¼éƒ½å¯ä»¥å®ç°ï¼š

```kotlin
fun <T> copyAll(to: MutableList<T>, from: MutableList<out T>) {
    to.addAll(from)
}

fun <T> copyAll(to: MutableList<in T>, from: MutableList<T>) {
    to.addAll(from)
}
```

`out` å…³é”®å­—å°±ç›¸å½“äº Java ä¸­çš„`<?  extends T>`ï¼Œå…¶ä½œç”¨å°±æ˜¯é™åˆ¶äº† `from` ä¸èƒ½ç”¨äºæ¥æ”¶å€¼è€Œåªèƒ½å‘å…¶å–å€¼ï¼Œè¿™æ ·å°±é¿å…äº†ä» `to` å–å‡ºå€¼ç„¶åå‘ `from` èµ‹å€¼è¿™ç§ä¸å®‰å…¨çš„è¡Œä¸ºäº†ï¼Œå³å®ç°äº†æ³›å‹åå˜

`in` å…³é”®å­—å°±ç›¸å½“äº Java ä¸­çš„`<? super T>`ï¼Œå…¶ä½œç”¨å°±æ˜¯é™åˆ¶äº† `to` åªèƒ½ç”¨äºæ¥æ”¶å€¼è€Œä¸èƒ½å‘å…¶å–å€¼ï¼Œè¿™æ ·å°±é¿å…äº†ä» `to` å–å‡ºå€¼ç„¶åå‘ `from` èµ‹å€¼è¿™ç§ä¸å®‰å…¨çš„è¡Œä¸ºäº†ï¼Œå³å®ç°äº†æ³›å‹é€†å˜

> ä»è¿™ä¹Ÿå¯ä»¥è”æƒ³åˆ°ï¼Œ`MutableList<*>` å°±ç›¸å½“äº `MutableList<out Any?>`äº†ï¼Œä¸¤è€…éƒ½å¸¦æœ‰ç›¸åŒçš„é™åˆ¶æ¡ä»¶ï¼šä¸å…è®¸å†™å€¼æ“ä½œï¼Œå…è®¸è¯»å€¼æ“ä½œï¼Œä¸”è¯»å–å‡ºæ¥çš„å€¼åªèƒ½å½“åš `Any?`è¿›è¡Œå¤„ç†

# åäºŒã€æ”¯æŒåå˜çš„ List

åœ¨ä¸Šè¿°ä¾‹å­ä¸­ï¼Œæƒ³è¦å®ç°åå˜è¿˜æœ‰å¦å¤–ä¸€ç§æ–¹å¼ï¼Œé‚£å°±æ˜¯ä½¿ç”¨ List

å°† from çš„ç±»å‹å£°æ˜ä» `MutableList<T>`ä¿®æ”¹ä¸º `List<T>` åï¼Œå¯ä»¥å‘ç° `copyAll` æ–¹æ³•ä¹Ÿå¯ä»¥æ­£å¸¸è°ƒç”¨äº†

```kotlin
fun <T> copyAll(to: MutableList<T>, from: List<T>) {
    to.addAll(from)
}
```

å¯¹ Kotlin æœ‰ä¸€å®šäº†è§£çš„åŒå­¦åº”è¯¥çŸ¥é“ï¼ŒKotlin ä¸­çš„é›†åˆæ¡†æ¶åˆ†ä¸ºä¸¤ç§å¤§ç±»ï¼š**å¯è¯»å¯å†™**å’Œ**åªèƒ½è¯»ä¸èƒ½å†™**

ä»¥ Java ä¸­çš„ ArrayList ä¸ºä¾‹ï¼ŒKotlin å°†ä¹‹åˆ†ä¸ºäº† MutableList å’Œ List ä¸¤ç§ç±»å‹çš„æ¥å£ã€‚è€Œ List æ¥å£ä¸­çš„æ³›å‹å·²ç»ä½¿ç”¨ out å…³é”®å­—è¿›è¡Œä¿®é¥°äº†ï¼Œä¸”ä¸åŒ…å«ä»»ä½•**ä¼ å…¥å€¼å¹¶ä¿å­˜**çš„æ–¹æ³•ï¼Œå³ List æ¥å£**åªæ”¯æŒè¯»å€¼è€Œä¸æ”¯æŒå†™å€¼**ï¼Œå…¶æœ¬èº«å°±å·²ç»æ»¡è¶³äº†åå˜æ‰€éœ€è¦çš„æ¡ä»¶ï¼Œå› æ­¤`copyAll` æ–¹æ³•å¯ä»¥æ­£å¸¸ä½¿ç”¨

```kotlin
public interface List<out E> : Collection<E> {
    override val size: Int
    override fun isEmpty(): Boolean
    override fun contains(element: @UnsafeVariance E): Boolean
    override fun iterator(): Iterator<E>
    override fun containsAll(elements: Collection<@UnsafeVariance E>): Boolean
    public operator fun get(index: Int): E
    public fun indexOf(element: @UnsafeVariance E): Int
    public fun lastIndexOf(element: @UnsafeVariance E): Int
    public fun listIterator(): ListIterator<E>
    public fun listIterator(index: Int): ListIterator<E>
    public fun subList(fromIndex: Int, toIndex: Int): List<E>
}
```

> è™½ç„¶ List æ¥å£ä¸­æœ‰å‡ ä¸ªæ–¹æ³•ä¹Ÿæ¥æ”¶äº† E ç±»å‹çš„å…¥å‚å‚æ•°ï¼Œä½†è¯¥æ–¹æ³•æœ¬èº«ä¸ä¼šè¿›è¡Œå†™å€¼æ“ä½œï¼Œæ‰€ä»¥å®é™…ä¸Šå¯ä»¥æ­£å¸¸ä½¿ç”¨ï¼ŒKotlin ä¹Ÿä½¿ç”¨ `@UnsafeVariance`æŠ‘åˆ¶äº†ç¼–è¯‘å™¨è­¦å‘Š

# åä¸‰ã€reified  &  inline

ä¸Šæ–‡è®²äº†ï¼Œç”±äºç±»å‹æ“¦é™¤ï¼ŒJava å’Œ Kotlin çš„æ³›å‹ç±»å‹å®å‚éƒ½ä¼šåœ¨ç¼–è¯‘é˜¶æ®µè¢«æ“¦é™¤ï¼Œåœ¨ Kotlin ä¸­å­˜åœ¨ä¸€ä¸ªé¢å¤–æ‰‹æ®µå¯ä»¥æ¥è§£å†³è¿™ä¸ªé—®é¢˜ï¼Œå³**å†…è”å‡½æ•°**

ç”¨å…³é”®å­— inline æ ‡è®°çš„å‡½æ•°å°±ç§°ä¸ºå†…è”å‡½æ•°ï¼Œå†ç”¨ reified å…³é”®å­—ä¿®é¥°å†…è”å‡½æ•°ä¸­çš„æ³›å‹å½¢å‚ï¼Œç¼–è¯‘å™¨åœ¨è¿›è¡Œç¼–è¯‘çš„æ—¶å€™ä¾¿ä¼šå°†å†…è”å‡½æ•°çš„å­—èŠ‚ç æ’å…¥åˆ°æ¯ä¸€ä¸ªè°ƒç”¨çš„åœ°æ–¹ï¼Œå½“ä¸­å°±åŒ…æ‹¬æ³›å‹çš„ç±»å‹å®å‚ã€‚è€Œå†…è”å‡½æ•°çš„ç±»å‹å½¢å‚èƒ½å¤Ÿè¢«å®åŒ–ï¼Œå°±æ„å‘³ç€æˆ‘ä»¬å¯ä»¥åœ¨è¿è¡Œæ—¶å¼•ç”¨å®é™…çš„ç±»å‹å®å‚äº†

ä¾‹å¦‚ï¼Œæˆ‘ä»¬å¯ä»¥å†™å‡ºä»¥ä¸‹è¿™æ ·çš„ä¸€ä¸ªå†…è”å‡½æ•°ï¼Œç”¨äºåˆ¤æ–­ä¸€ä¸ªå¯¹è±¡æ˜¯å¦æ˜¯æŒ‡å®šç±»å‹

```kotlin
fun main() {
    println(1.isInstanceOf<String>())
    println("string".isInstanceOf<Int>())
}

inline fun <reified T> Any.isInstanceOf(): Boolean {
    return this is T
}
```

å°†ä»¥ä¸Šçš„ Kotlin ä»£ç åç¼–è¯‘ä¸º Java ä»£ç ï¼Œå¯ä»¥çœ‹å‡ºæ¥ `main()`æ–¹æ³•æœ€ç»ˆæ˜¯æ²¡æœ‰è°ƒç”¨ `isInstanceOf` æ–¹æ³•çš„ï¼Œå…·ä½“çš„åˆ¤æ–­é€»è¾‘éƒ½è¢«æ’å…¥åˆ°äº†`main()`æ–¹æ³•å†…éƒ¨ï¼Œæœ€ç»ˆæ˜¯æ‰§è¡Œäº† `instanceof` æ“ä½œï¼Œä¸”æŒ‡å®šäº†å…·ä½“çš„æ³›å‹ç±»å‹å‚æ•° String å’Œ Integer

```java
public final class GenericTest6Kt {
   public static final void main() {
      Object $this$isInstanceOf$iv = 1;
      int $i$f$isInstanceOf = false;
      boolean var2 = $this$isInstanceOf$iv instanceof String;
      $i$f$isInstanceOf = false;
      System.out.println(var2);
      Object $this$isInstanceOf$iv = "string";
      $i$f$isInstanceOf = false;
      var2 = $this$isInstanceOf$iv instanceof Integer;
      $i$f$isInstanceOf = false;
      System.out.println(var2);
   }

   // $FF: synthetic method
   public static void main(String[] var0) {
      main();
   }

   // $FF: synthetic method
   public static final boolean isInstanceOf(Object $this$isInstanceOf) {
      int $i$f$isInstanceOf = 0;
      Intrinsics.checkNotNullParameter($this$isInstanceOf, "$this$isInstanceOf");
      Intrinsics.reifiedOperationMarker(3, "T");
      return $this$isInstanceOf instanceof Object;
   }
}
```

inline å’Œ reified æ¯”è¾ƒæœ‰ç”¨çš„ä¸€ä¸ªåœºæ™¯æ˜¯ç”¨åœ¨ Gson ååºåˆ—çš„æ—¶å€™ã€‚ç”±äºæ³›å‹è¿è¡Œæ—¶**ç±»å‹æ“¦é™¤**çš„é—®é¢˜ï¼Œç›®å‰ç”¨ Gson ååºåˆ—åŒ–æ³›å‹ç±»æ—¶æ­¥éª¤æ˜¯æ¯”è¾ƒç¹ççš„ï¼Œåˆ©ç”¨ inline å’Œ reified æˆ‘ä»¬å°±å¯ä»¥ç®€åŒ–å¾ˆå¤šæ“ä½œ

```kotlin
val gson = Gson()

inline fun <reified T> toBean(json: String): T {
    return gson.fromJson(json, T::class.java)
}

data class BlogBean(val name: String, val url: String)

fun main() {
    val json = """{"name":"ä¸šå¿—é™ˆ","url":"https://juejin.cn/user/923245496518439"}"""
    val listJson = """[{"name":"ä¸šå¿—é™ˆ","url":"https://juejin.cn/user/923245496518439"},{"name":"ä¸šå¿—é™ˆ","url":"https://juejin.cn/user/923245496518439"}]"""

    val blogBean = toBean<BlogBean>(json)
    val blogMap = toBean<Map<String, String>>(json)
    val blogBeanList = toBean<List<BlogBean>>(listJson)
    
    //BlogBean(name=ä¸šå¿—é™ˆ, url=https://juejin.cn/user/923245496518439)
    println(blogBean)
    //{name=ä¸šå¿—é™ˆ, url=https://juejin.cn/user/923245496518439}
    println(blogMap)
    //[{name=ä¸šå¿—é™ˆ, url=https://juejin.cn/user/923245496518439}, {name=ä¸šå¿—é™ˆ, url=https://juejin.cn/user/923245496518439}]
    println(blogBeanList)
}
```

æˆ‘ä¹Ÿåˆ©ç”¨ Kotlin çš„è¿™ä¸ªå¼ºå¤§ç‰¹æ€§å†™äº†ä¸€ä¸ªç”¨äºç®€åŒ– Java / Kotlin å¹³å°çš„åºåˆ—åŒ–å’Œååºåˆ—åŒ–æ“ä½œçš„åº“ï¼š[JsonHolder](https://github.com/leavesCZY/JsonHolder)

# åå››ã€æ€»ç»“

æœ€åæ¥åšä¸ªç®€å•çš„æ€»ç»“

|        | åå˜                                               | é€†å˜                                                         | ä¸å˜                        |
| ------ | -------------------------------------------------- | ------------------------------------------------------------ | --------------------------- |
| Kotlin | `<out T>`ï¼Œåªèƒ½ä½œä¸ºæ¶ˆè´¹è€…ï¼Œåªèƒ½è¯»å–ä¸èƒ½æ·»åŠ         | `<in T>`ï¼Œåªèƒ½ä½œä¸ºç”Ÿäº§è€…ï¼Œåªèƒ½æ·»åŠ ï¼Œè¯»å–å‡ºçš„å€¼åªèƒ½å½“åš Any ç±»å‹ | `<T>`ï¼Œæ—¢å¯ä»¥æ·»åŠ ä¹Ÿå¯ä»¥è¯»å– |
| Java   | `<?  extends T>`ï¼Œåªèƒ½ä½œä¸ºæ¶ˆè´¹è€…ï¼Œåªèƒ½è¯»å–ä¸èƒ½æ·»åŠ  | `<? super T>`ï¼Œåªèƒ½ä½œä¸ºç”Ÿäº§è€…ï¼Œåªèƒ½æ·»åŠ ï¼Œè¯»å–å‡ºçš„å€¼åªèƒ½å½“åš Object ç±»å‹ | `<T>`ï¼Œæ—¢å¯ä»¥æ·»åŠ ä¹Ÿå¯ä»¥è¯»å– |